[{"lot_date":"01-09-2019","lot_3up":"798787","lot_2down":"20","lot_3down":"210 , 847 , 439 , 274"},{"lot_date":"16-08-2019","lot_3up":"775476","lot_2down":"89","lot_3down":"149 , 912 , 563 , 580"},{"lot_date":"01-08-2019","lot_3up":"387006","lot_2down":"58","lot_3down":"983 , 135 , 795 , 562"},{"lot_date":"15-07-2019","lot_3up":"369765","lot_2down":"88","lot_3down":"901 , 355 , 556 , 113"},{"lot_date":"01-07-2019","lot_3up":"943647","lot_2down":"86","lot_3down":"864 , 239 , 375 , 006"},{"lot_date":"16-06-2019","lot_3up":"174055","lot_2down":"29","lot_3down":"884 , 625 , 800 , 127"},{"lot_date":"01-06-2019","lot_3up":"516461","lot_2down":"46","lot_3down":"589 , 713 , 560 , 215"},{"lot_date":"16-05-2019","lot_3up":"962526","lot_2down":"71","lot_3down":"949 , 669 , 828 , 018"},{"lot_date":"02-05-2019","lot_3up":"061324","lot_2down":"25","lot_3down":"043 , 476 , 699 , 374"},{"lot_date":"16-04-2019","lot_3up":"570331","lot_2down":"23","lot_3down":"930 , 512 , 966 , 968"},{"lot_date":"01-04-2019","lot_3up":"109767","lot_2down":"52","lot_3down":"888 , 959 , 403 , 975"},{"lot_date":"16-03-2019","lot_3up":"724628","lot_2down":"64","lot_3down":"883 , 148 , 877 , 154"},{"lot_date":"01-03-2019","lot_3up":"345650","lot_2down":"65","lot_3down":"999 , 137 , 830 , 837"},{"lot_date":"16-02-2019","lot_3up":"074824","lot_2down":"56","lot_3down":"881 , 910 , 879 , 612"},{"lot_date":"01-02-2019","lot_3up":"967134","lot_2down":"04","lot_3down":"643 , 779 , 948 , 197"},{"lot_date":"17-01-2019","lot_3up":"197079","lot_2down":"65","lot_3down":"206 , 412 , 660 , 127"},{"lot_date":"30-12-2018","lot_3up":"735867","lot_2down":"02","lot_3down":"913 , 031 , 701 , 884"},{"lot_date":"16-12-2018","lot_3up":"356564","lot_2down":"62","lot_3down":"480 , 948 , 369 , 297"},{"lot_date":"01-12-2018","lot_3up":"021840","lot_2down":"67","lot_3down":"405 , 370 , 988 , 561"},{"lot_date":"16-11-2018","lot_3up":"989903","lot_2down":"16","lot_3down":"930 , 471 , 140 , 876"}]